{
  "event_type": "retention.restoration_completed",
  "version": "v1",
  "producer": "M68-Retention-Service",
  "event_class": "domain",
  "partition_key_path": "data.entity_id",
  "payload_schema": {
    "type": "object",
    "required": ["restoration_id", "entity_id", "data_type", "restored_at", "status"],
    "properties": {
      "restoration_id": { "type": "string" },
      "entity_id": { "type": "string" },
      "data_type": { "type": "string" },
      "restored_at": { "type": "string", "format": "date-time" },
      "status": { "type": "string" },
      "restored_by": { "type": "string" }
    }
  }
}
